cstmodels/__init__.py
cstmodels/layers.py
cstmodels/models.py
cstmodels-0.1.1.dist-info/METADATA
cstmodels-0.1.1.dist-info/WHEEL
cstmodels-0.1.1.dist-info/licenses/LICENSE
cstmodels-0.1.1.dist-info/RECORD
