Metadata-Version: 2.4
Name: cstmodels
Version: 0.1.1
Summary: This package provides the reference implementation of the Convolutional Set Transformer (Chinello & Boracchi, 2025). It includes reusable Keras 3 layers for building CST architectures, and provides an easy interface to load and use the CST-15 model pre-trained on ImageNet.
Project-URL: Homepage, https://chinefed.github.io/convolutional-set-transformer/
Project-URL: Source, https://github.com/chinefed/convolutional-set-transformer
Project-URL: Documentation, https://chinefed.github.io/convolutional-set-transformer/
Author-email: Federico Chinello <federico.chinello@studbocconi.it>
License: MIT License
License-File: LICENSE
Requires-Python: >=3.8
Requires-Dist: keras>=3.0.0
Requires-Dist: numpy>=1.24
Requires-Dist: tensorflow>=2.15.0
